{
  "dataStores": [
    {
      "id": "sentinelhub",
      "name": "SENTINEL Hub",
      "datasets": [
        {
          "id": "S2L1C",
          "name": "S2L1C",
          "variables": [
            {
              "id": "B01",
              "name": "B01"
            },
            {
              "id": "B02",
              "name": "B02"
            },
            {
              "id": "B03",
              "name": "B03"
            },
            {
              "id": "B04",
              "name": "B04"
            },
            {
              "id": "B05",
              "name": "B05"
            },
            {
              "id": "B06",
              "name": "B06"
            },
            {
              "id": "B07",
              "name": "B07"
            },
            {
              "id": "B08",
              "name": "B08"
            },
            {
              "id": "B09",
              "name": "B09"
            },
            {
              "id": "B10",
              "name": "B10"
            },
            {
              "id": "B11",
              "name": "B11"
            },
            {
              "id": "B12",
              "name": "B12"
            },
            {
              "id": "B13",
              "name": "B13"
            },
            {
              "id": "B14",
              "name": "B14"
            },
            {
              "id": "B15",
              "name": "B15"
            }
          ]
        },
        {
          "id": "S2L2A",
          "name": "S2L2A",
          "variables": [
            {
              "id": "B01",
              "name": "B01"
            },
            {
              "id": "B02",
              "name": "B02"
            },
            {
              "id": "B03",
              "name": "B03"
            },
            {
              "id": "B04",
              "name": "B04"
            },
            {
              "id": "B05",
              "name": "B05"
            },
            {
              "id": "B06",
              "name": "B06"
            },
            {
              "id": "B07",
              "name": "B07"
            },
            {
              "id": "B08",
              "name": "B08"
            },
            {
              "id": "B09",
              "name": "B09"
            },
            {
              "id": "B10",
              "name": "B10"
            },
            {
              "id": "B11",
              "name": "B11"
            },
            {
              "id": "B12",
              "name": "B12"
            },
            {
              "id": "B13",
              "name": "B13"
            },
            {
              "id": "B14",
              "name": "B14"
            },
            {
              "id": "B15",
              "name": "B15"
            }
          ]
        }
      ]
    },
    {
      "id": "cciodp",
      "name": "ESA CCI Open Data Portal",
      "datasets": [
        {
          "id": "esacci.OZONE.month.L3.NP.multi-sensor.multi-platform.MERGED.fv0002.r1",
          "name": "ESA Ozone Climate Change Initiative (Ozone CCI): Level 3 Nadir Ozone Profile Merged Data Product, version 2",
          "fid": "4eb4e801424a47f7b77434291921f889",
          "variables": [
            {
              "id": "surface_pressure",
              "units": "hPa",
              "name": "Pressure at the bottom of the atmosphere."
            },
            {
              "id": "air_pressure",
              "units": "hPa",
              "name": "air pressure at layer boundaries"
            },
            {
              "id": "O3e_ndens",
              "units": "6.02214E-17 mol m-3",
              "name": "error in the weighted average of the number density (#molecules/cm3)"
            },
            {
              "id": "O3e_du",
              "units": "446.15E-6 mol m-2",
              "name": "error in the weighted average of the partial ozone columns (DU/layer)"
            },
            {
              "id": "O3e_vmr",
              "units": "1e-6",
              "name": "error in the weighted average of the volume mixing ratio (ppmv)"
            },
            {
              "id": "layers",
              "units": "1",
              "name": "model_level_number == layer number, starting at 1"
            },
            {
              "id": "O3e_du_tot",
              "units": "446.15E-6 mol m-2",
              "name": "total column error: quadratically added o3e_du (DU)"
            },
            {
              "id": "O3_du_tot",
              "units": "446.15E-6 mol m-2",
              "name": "total column: vertically integrated O3_du dataset (DU)"
            },
            {
              "id": "O3_ndens",
              "units": "6.02214E-17 mol m-3",
              "name": "weighted average of the number density (#molecules/cm3)"
            },
            {
              "id": "O3_du",
              "units": "446.15E-6 mol m-2",
              "name": "weighted average of the partial ozone columns (DU/layer)"
            },
            {
              "id": "O3_vmr",
              "units": "1e-6",
              "name": "weighted average of the volume mixing ratio (ppmv)"
            }
          ]
        },
        {
          "id": "esacci.OZONE.day.L3S.TC.multi-sensor.multi-platform.MERGED.fv0100.r1",
          "name": "ESA Ozone Climate Change Initiative (Ozone CCI): Level 3 Total Ozone Merged Data Product, version 01",
          "fid": "0d2260ad4e2c42b6b14fe5b3308f5eaa",
          "variables": [
            {
              "id": "atmosphere_mole_content_of_ozone",
              "units": "DU",
              "name": "Mean Total Ozone Column in Dobson Units"
            },
            {
              "id": "atmosphere_mole_content_of_ozone_standard_deviation",
              "units": "DU",
              "name": "Standard Deviation of the Mean Total Ozone Column in Dobson Units"
            },
            {
              "id": "atmosphere_mole_content_of_ozone_standard_error",
              "units": "DU",
              "name": "Standard Error of the Mean Total Ozone Column in Dobson Units"
            },
            {
              "id": "atmosphere_mole_content_of_ozone_number_of_observations",
              "units": "1",
              "name": "The number of measurements use to derive the Mean Total Ozone Column in Dobson Units"
            }
          ]
        },
        {
          "id": "esacci.OZONE.month.L3.LP.SMR.ODIN.MZM.v0001.r1",
          "name": "ESA Ozone Climate Change Initiative (Ozone CCI): ODIN/SMR (544.6 GHz) Level 3 Limb Ozone Monthly Zonal Mean (MZM) Profiles, Version 1",
          "fid": "fe651dbef5d44248bef70906f4b3d12b",
          "variables": [
            {
              "id": "sample_standard_deviation",
              "units": "%",
              "name": "Sample standard deviation in 1 month x10 deg bins"
            },
            {
              "id": "approximate_altitude",
              "units": "km",
              "name": "approximate altitude corresponding to pressure levels"
            },
            {
              "id": "latitude_centers",
              "units": "degrees_north",
              "name": "centers of latitude bins"
            },
            {
              "id": "inhomogeneity_in_latitude",
              "units": "1",
              "name": "inhomogeneity measure in latitude"
            },
            {
              "id": "inhomogeneity_in_time",
              "units": "1",
              "name": "inhomogeneity measure in time"
            },
            {
              "id": "mean_uncertainty_estimate",
              "units": "%",
              "name": "mean of error estimates"
            },
            {
              "id": "standard_error_of_the_mean",
              "units": "%",
              "name": "uncertainty of the monthly zonal mean data"
            },
            {
              "id": "air_pressure",
              "units": "hPa",
              "name": "air_pressure"
            },
            {
              "id": "ozone_mole_concentation",
              "units": "mol cm-3",
              "name": "ozone_mole_concentation"
            },
            {
              "id": "ozone_mixing_ratio",
              "units": "1",
              "name": "ozone_mixing_ratio"
            }
          ]
        },
        {
          "id": "esacci.CLOUD.month.L3C.CLD_PRODUCTS.MODIS.Terra.MODIS_TERRA.2-0.r1",
          "name": "ESA Cloud Climate Change Initiative (Cloud_cci): MODIS-TERRA monthly gridded cloud properties, version 2.0",
          "fid": "f1ab07b5292f4813bd3090b51d270aa8",
          "variables": [
            {
              "id": "hist1d_cer_bin_border",
              "units": "um",
              "name": "cer histogram bin border values"
            },
            {
              "id": "hist1d_cer_bin_centre",
              "units": "um",
              "name": "cer histogram bin centres"
            },
            {
              "id": "hist1d_cla_vis006_bin_centre",
              "units": "1",
              "name": "cloud abedo1 histogram bin centres"
            },
            {
              "id": "cla_vis006_corr_unc",
              "units": "1",
              "name": "cloud albedo at 0.6 um correlated uncertainty"
            },
            {
              "id": "cla_vis006_prop_unc",
              "units": "1",
              "name": "cloud albedo at 0.6 um propagated uncertainty"
            },
            {
              "id": "cla_vis006_std",
              "units": "1",
              "name": "cloud albedo at 0.6 um standard deviation"
            },
            {
              "id": "cla_vis006_unc",
              "units": "1",
              "name": "cloud albedo at 0.6 um uncertainty"
            },
            {
              "id": "cla_vis006",
              "units": "1",
              "name": "cloud albedo at 0.6 um"
            },
            {
              "id": "cla_vis008_corr_unc",
              "units": "1",
              "name": "cloud albedo at 0.8 um correlated uncertainty"
            },
            {
              "id": "cla_vis008_prop_unc",
              "units": "1",
              "name": "cloud albedo at 0.8 um propagated uncertainty"
            },
            {
              "id": "cla_vis008_std",
              "units": "1",
              "name": "cloud albedo at 0.8 um standard deviation"
            },
            {
              "id": "cla_vis008_unc",
              "units": "1",
              "name": "cloud albedo at 0.8 um uncertainty"
            },
            {
              "id": "cla_vis008",
              "units": "1",
              "name": "cloud albedo at 0.8 um"
            },
            {
              "id": "hist1d_cla_vis006_bin_border",
              "units": "1",
              "name": "cloud albedo1 histogram bin border values"
            },
            {
              "id": "hist1d_cla_vis008_bin_border",
              "units": "1",
              "name": "cloud albedo2 histogram bin border values"
            },
            {
              "id": "hist1d_cla_vis008_bin_centre",
              "units": "1",
              "name": "cloud albedo2 histogram bin centres"
            },
            {
              "id": "cee_corr_unc",
              "units": "1",
              "name": "cloud effective emissivity at 10.8 um correlated uncertainty"
            },
            {
              "id": "cee_prop_unc",
              "units": "1",
              "name": "cloud effective emissivity at 10.8 um propagated uncertainty"
            },
            {
              "id": "cee_std",
              "units": "1",
              "name": "cloud effective emissivity at 10.8 um standard deviation"
            },
            {
              "id": "cee_unc",
              "units": "1",
              "name": "cloud effective emissivity at 10.8 um uncertainty"
            },
            {
              "id": "cee",
              "units": "1",
              "name": "cloud effective emissivity at 10.8 um"
            },
            {
              "id": "cer_corr_unc",
              "units": "um",
              "name": "cloud effective radius correlated uncertainty"
            },
            {
              "id": "cer_prop_unc",
              "units": "um",
              "name": "cloud effective radius propagated uncertainty"
            },
            {
              "id": "cer_std",
              "units": "um",
              "name": "cloud effective radius standard deviation"
            },
            {
              "id": "cer_unc",
              "units": "um",
              "name": "cloud effective radius uncertainty"
            },
            {
              "id": "cer",
              "units": "um",
              "name": "cloud effective radius"
            },
            {
              "id": "cfc_corr_unc",
              "units": "%",
              "name": "cloud fraction correlated uncertainty"
            },
            {
              "id": "cfc_day",
              "units": "1",
              "name": "cloud fraction day"
            },
            {
              "id": "cfc_night",
              "units": "1",
              "name": "cloud fraction night"
            },
            {
              "id": "cfc_prop_unc",
              "units": "%",
              "name": "cloud fraction propagated uncertainty"
            },
            {
              "id": "cfc_std",
              "units": "1",
              "name": "cloud fraction standard deviation"
            },
            {
              "id": "cfc_twl",
              "units": "1",
              "name": "cloud fraction twilight"
            },
            {
              "id": "cfc_unc",
              "units": "%",
              "name": "cloud fraction uncertainty"
            },
            {
              "id": "cfc",
              "units": "1",
              "name": "cloud fraction"
            },
            {
              "id": "iwp_corr_unc",
              "units": "g/m2",
              "name": "cloud ice water path correlated uncertainty"
            },
            {
              "id": "iwp_prop_unc",
              "units": "g/m2",
              "name": "cloud ice water path propagated uncertainty"
            },
            {
              "id": "iwp_std",
              "units": "g/m2",
              "name": "cloud ice water path standard deviation"
            },
            {
              "id": "iwp_unc",
              "units": "g/m2",
              "name": "cloud ice water path uncertainty"
            },
            {
              "id": "iwp",
              "units": "g/m2",
              "name": "cloud ice water path"
            },
            {
              "id": "lwp_corr_unc",
              "units": "g/m2",
              "name": "cloud liquid water path correlated uncertainty"
            },
            {
              "id": "lwp_prop_unc",
              "units": "g/m2",
              "name": "cloud liquid water path propagated uncertainty"
            },
            {
              "id": "lwp_std",
              "units": "g/m2",
              "name": "cloud liquid water path standard deviation"
            },
            {
              "id": "lwp_unc",
              "units": "g/m2",
              "name": "cloud liquid water path uncertainty"
            },
            {
              "id": "lwp",
              "units": "g/m2",
              "name": "cloud liquid water path"
            },
            {
              "id": "cot_corr_unc",
              "units": "1",
              "name": "cloud optical thickness correlated uncertainty"
            },
            {
              "id": "cot_log",
              "units": "1",
              "name": "cloud optical thickness logarithmically averaged"
            },
            {
              "id": "cot_prop_unc",
              "units": "1",
              "name": "cloud optical thickness propagated uncertainty"
            },
            {
              "id": "cot_std",
              "units": "1",
              "name": "cloud optical thickness standard deviation"
            },
            {
              "id": "cot_unc",
              "units": "1",
              "name": "cloud optical thickness uncertainty"
            },
            {
              "id": "cot",
              "units": "1",
              "name": "cloud optical thickness"
            },
            {
              "id": "cth_corr_unc",
              "units": "km",
              "name": "cloud top height correlated uncertainty"
            },
            {
              "id": "cth_corrected_corr_unc",
              "units": "km",
              "name": "cloud top height correlated uncertainty"
            },
            {
              "id": "cth_corrected_prop_unc",
              "units": "km",
              "name": "cloud top height propagated uncertainty"
            },
            {
              "id": "cth_prop_unc",
              "units": "km",
              "name": "cloud top height propagated uncertainty"
            },
            {
              "id": "cth_corrected_std",
              "units": "km",
              "name": "cloud top height standard deviation"
            },
            {
              "id": "cth_std",
              "units": "km",
              "name": "cloud top height standard deviation"
            },
            {
              "id": "cth_corrected_unc",
              "units": "km",
              "name": "cloud top height uncertainty"
            },
            {
              "id": "cth_unc",
              "units": "km",
              "name": "cloud top height uncertainty"
            },
            {
              "id": "cth",
              "units": "km",
              "name": "cloud top height"
            },
            {
              "id": "cth_corrected",
              "units": "km",
              "name": "cloud top height"
            },
            {
              "id": "ctp_corr_unc",
              "units": "hPa",
              "name": "cloud top pressure correlated uncertainty"
            },
            {
              "id": "ctp_corrected_corr_unc",
              "units": "hPa",
              "name": "cloud top pressure correlated uncertainty"
            },
            {
              "id": "ctp_log",
              "units": "hPa",
              "name": "cloud top pressure logarithmically averaged"
            },
            {
              "id": "ctp_corrected_prop_unc",
              "units": "hPa",
              "name": "cloud top pressure propagated uncertainty"
            },
            {
              "id": "ctp_prop_unc",
              "units": "hPa",
              "name": "cloud top pressure propagated uncertainty"
            },
            {
              "id": "ctp_corrected_std",
              "units": "hPa",
              "name": "cloud top pressure standard deviation"
            },
            {
              "id": "ctp_std",
              "units": "hPa",
              "name": "cloud top pressure standard deviation"
            },
            {
              "id": "ctp_corrected_unc",
              "units": "hPa",
              "name": "cloud top pressure uncertainty"
            },
            {
              "id": "ctp_unc",
              "units": "hPa",
              "name": "cloud top pressure uncertainty"
            },
            {
              "id": "ctp",
              "units": "hPa",
              "name": "cloud top pressure"
            },
            {
              "id": "ctp_corrected",
              "units": "hPa",
              "name": "cloud top pressure"
            },
            {
              "id": "ctt_corr_unc",
              "units": "K",
              "name": "cloud top temperature correlated uncertainty"
            },
            {
              "id": "ctt_corrected_corr_unc",
              "units": "K",
              "name": "cloud top temperature correlated uncertainty"
            },
            {
              "id": "ctt_corrected_prop_unc",
              "units": "K",
              "name": "cloud top temperature propagated uncertainty"
            },
            {
              "id": "ctt_prop_unc",
              "units": "K",
              "name": "cloud top temperature propagated uncertainty"
            },
            {
              "id": "ctt_corrected_std",
              "units": "K",
              "name": "cloud top temperature standard deviation"
            },
            {
              "id": "ctt_std",
              "units": "K",
              "name": "cloud top temperature standard deviation"
            },
            {
              "id": "ctt_corrected_unc",
              "units": "K",
              "name": "cloud top temperature uncertainty"
            },
            {
              "id": "ctt_unc",
              "units": "K",
              "name": "cloud top temperature uncertainty"
            },
            {
              "id": "ctt",
              "units": "K",
              "name": "cloud top temperature"
            },
            {
              "id": "ctt_corrected",
              "units": "K",
              "name": "cloud top temperature"
            },
            {
              "id": "hist1d_cot_bin_border",
              "units": "1",
              "name": "cot histogram bin border values"
            },
            {
              "id": "hist2d_cot_bin_border",
              "units": "1",
              "name": "cot histogram bin border values"
            },
            {
              "id": "hist1d_cot_bin_centre",
              "units": "1",
              "name": "cot histogram bin centres"
            },
            {
              "id": "hist2d_cot_bin_centre",
              "units": "1",
              "name": "cot histogram bin centres"
            },
            {
              "id": "hist1d_ctp_bin_border",
              "units": "hPa",
              "name": "ctp histogram bin border values"
            },
            {
              "id": "hist2d_ctp_bin_border",
              "units": "hPa",
              "name": "ctp histogram bin border values"
            },
            {
              "id": "hist1d_ctp_bin_centre",
              "units": "hPa",
              "name": "ctp histogram bin centres"
            },
            {
              "id": "hist2d_ctp_bin_centre",
              "units": "hPa",
              "name": "ctp histogram bin centres"
            },
            {
              "id": "hist1d_ctt_bin_border",
              "units": "K",
              "name": "ctt histogram bin border values"
            },
            {
              "id": "hist1d_ctt_bin_centre",
              "units": "K",
              "name": "ctt histogram bin centres"
            },
            {
              "id": "hist1d_cwp_bin_border",
              "units": "g/m2",
              "name": "cwp histogram bin border values"
            },
            {
              "id": "hist1d_cwp_bin_centre",
              "units": "g/m2",
              "name": "cwp histogram bin centres"
            },
            {
              "id": "cph_day_std",
              "units": "1",
              "name": "daytime fraction of liquid water clouds standard deviation"
            },
            {
              "id": "cph_day",
              "units": "1",
              "name": "daytime fraction of liquid water clouds"
            },
            {
              "id": "cph_std",
              "units": "1",
              "name": "fraction of liquid water clouds standard deviation"
            },
            {
              "id": "cph",
              "units": "1",
              "name": "fraction of liquid water clouds"
            },
            {
              "id": "iwp_allsky",
              "units": "g/m2",
              "name": "grid box mean of cloud ice water path"
            },
            {
              "id": "lwp_allsky",
              "units": "g/m2",
              "name": "grid box mean of cloud liquid water path"
            },
            {
              "id": "cfc_high",
              "units": "1",
              "name": "high level cloud fraction"
            },
            {
              "id": "hist1d_cla_vis006",
              "units": "1",
              "name": "histogram of cloud albedo at 0.6 um"
            },
            {
              "id": "hist1d_cla_vis008",
              "units": "1",
              "name": "histogram of cloud albedo at 0.8 um"
            },
            {
              "id": "hist1d_cer",
              "units": "1",
              "name": "histogram of cloud effective radius"
            },
            {
              "id": "hist1d_cot",
              "units": "1",
              "name": "histogram of cloud optical thickness"
            },
            {
              "id": "hist1d_ctp",
              "units": "1",
              "name": "histogram of cloud top pressure"
            },
            {
              "id": "hist1d_ctt",
              "units": "1",
              "name": "histogram of cloud top temperature"
            },
            {
              "id": "hist1d_cwp",
              "units": "1",
              "name": "histogram of cloud water path"
            },
            {
              "id": "cla_vis006_ice_std",
              "units": "1",
              "name": "ice water cloud albedo at 0.6 um standard deviation"
            },
            {
              "id": "cla_vis006_ice_unc",
              "units": "1",
              "name": "ice water cloud albedo at 0.6 um uncertainty"
            },
            {
              "id": "cla_vis006_ice",
              "units": "1",
              "name": "ice water cloud albedo at 0.6 um"
            },
            {
              "id": "cla_vis008_ice_std",
              "units": "1",
              "name": "ice water cloud albedo at 0.8 um standard deviation"
            },
            {
              "id": "cla_vis008_ice_unc",
              "units": "1",
              "name": "ice water cloud albedo at 0.8 um uncertainty"
            },
            {
              "id": "cla_vis008_ice",
              "units": "1",
              "name": "ice water cloud albedo at 0.8 um"
            },
            {
              "id": "cer_ice_corr_unc",
              "units": "um",
              "name": "ice water cloud effective radius correlated uncertainty"
            },
            {
              "id": "cer_ice_prop_unc",
              "units": "um",
              "name": "ice water cloud effective radius propagated uncertainty"
            },
            {
              "id": "cer_ice_std",
              "units": "um",
              "name": "ice water cloud effective radius standard deviation"
            },
            {
              "id": "cer_ice_unc",
              "units": "um",
              "name": "ice water cloud effective radius uncertainty"
            },
            {
              "id": "cer_ice",
              "units": "um",
              "name": "ice water cloud effective radius"
            },
            {
              "id": "cot_ice_corr_unc",
              "units": "1",
              "name": "ice water cloud optical thickness correlated uncertainty"
            },
            {
              "id": "cot_ice_prop_unc",
              "units": "1",
              "name": "ice water cloud optical thickness propagated uncertainty"
            },
            {
              "id": "cot_ice_std",
              "units": "1",
              "name": "ice water cloud optical thickness standard deviation"
            },
            {
              "id": "cot_ice_unc",
              "units": "1",
              "name": "ice water cloud optical thickness uncertainty"
            },
            {
              "id": "cot_ice",
              "units": "1",
              "name": "ice water cloud optical thickness"
            },
            {
              "id": "hist2d_cot_ctp",
              "units": "1",
              "name": "joint histogram of cloud optical thickness and cloud top pressure"
            },
            {
              "id": "lat",
              "units": "degrees_north",
              "name": "latitude"
            },
            {
              "id": "cla_vis006_liq_std",
              "units": "1",
              "name": "liquid water cloud albedo at 0.6 um standard deviation"
            },
            {
              "id": "cla_vis006_liq_unc",
              "units": "1",
              "name": "liquid water cloud albedo at 0.6 um uncertainty"
            },
            {
              "id": "cla_vis006_liq",
              "units": "1",
              "name": "liquid water cloud albedo at 0.6 um"
            },
            {
              "id": "cla_vis008_liq_std",
              "units": "1",
              "name": "liquid water cloud albedo at 0.8 um standard deviation"
            },
            {
              "id": "cla_vis008_liq_unc",
              "units": "1",
              "name": "liquid water cloud albedo at 0.8 um uncertainty"
            },
            {
              "id": "cla_vis008_liq",
              "units": "1",
              "name": "liquid water cloud albedo at 0.8 um"
            },
            {
              "id": "cer_liq_corr_unc",
              "units": "um",
              "name": "liquid water cloud effective radius correlated uncertainty"
            },
            {
              "id": "cer_liq_prop_unc",
              "units": "um",
              "name": "liquid water cloud effective radius propagated uncertainty"
            },
            {
              "id": "cer_liq_std",
              "units": "um",
              "name": "liquid water cloud effective radius standard deviation"
            },
            {
              "id": "cer_liq_unc",
              "units": "um",
              "name": "liquid water cloud effective radius uncertainty"
            },
            {
              "id": "cer_liq",
              "units": "um",
              "name": "liquid water cloud effective radius"
            },
            {
              "id": "cot_liq_corr_unc",
              "units": "1",
              "name": "liquid water cloud optical thickness correlated uncertainty"
            },
            {
              "id": "cot_liq_prop_unc",
              "units": "1",
              "name": "liquid water cloud optical thickness propagated uncertainty"
            },
            {
              "id": "cot_liq_std",
              "units": "1",
              "name": "liquid water cloud optical thickness standard deviation"
            },
            {
              "id": "cot_liq_unc",
              "units": "1",
              "name": "liquid water cloud optical thickness uncertainty"
            },
            {
              "id": "cot_liq",
              "units": "1",
              "name": "liquid water cloud optical thickness"
            },
            {
              "id": "lon",
              "units": "degrees_east",
              "name": "longitude"
            },
            {
              "id": "cfc_low",
              "units": "1",
              "name": "low level cloud fraction"
            },
            {
              "id": "cfc_mid",
              "units": "1",
              "name": "mid level cloud fraction"
            },
            {
              "id": "nobs_clear_day",
              "units": "1",
              "name": "number of clear daytime observations"
            },
            {
              "id": "nobs_clear_night",
              "units": "1",
              "name": "number of clear nighttime observations"
            },
            {
              "id": "nobs_clear_twl",
              "units": "1",
              "name": "number of clear twilight observations"
            },
            {
              "id": "nobs_cloudy_day",
              "units": "1",
              "name": "number of cloudy daytime observations"
            },
            {
              "id": "nobs_cloudy_night",
              "units": "1",
              "name": "number of cloudy nighttime observations"
            },
            {
              "id": "nobs_cloudy",
              "units": "1",
              "name": "number of cloudy observations"
            },
            {
              "id": "nobs_cloudy_twl",
              "units": "1",
              "name": "number of cloudy twilight observations"
            },
            {
              "id": "nobs_day",
              "units": "1",
              "name": "number of daytime observations"
            },
            {
              "id": "nobs",
              "units": "1",
              "name": "number of observations"
            },
            {
              "id": "nretr_cloudy",
              "units": "1",
              "name": "number of valid cloudy retrievals"
            },
            {
              "id": "nretr_cloudy_day",
              "units": "1",
              "name": "number of valid daytime cloudy retrievals"
            },
            {
              "id": "nretr_cloudy_high",
              "units": "1",
              "name": "number of valid high level cloudy retrievals"
            },
            {
              "id": "nretr_cloudy_ice",
              "units": "1",
              "name": "number of valid ice phase cloudy retrievals"
            },
            {
              "id": "nretr_cloudy_day_ice",
              "units": "1",
              "name": "number of valid ice phase daytime cloudy retrievals"
            },
            {
              "id": "nretr_cloudy_liq",
              "units": "1",
              "name": "number of valid liquid phase cloudy retrievals"
            },
            {
              "id": "nretr_cloudy_day_liq",
              "units": "1",
              "name": "number of valid liquid phase daytime cloudy retrievals"
            },
            {
              "id": "nretr_cloudy_low",
              "units": "1",
              "name": "number of valid low level cloudy retrievals"
            },
            {
              "id": "nretr_cloudy_mid",
              "units": "1",
              "name": "number of valid mid level cloudy retrievals"
            },
            {
              "id": "hist_phase",
              "units": "1",
              "name": "phase histogram bins"
            },
            {
              "id": "stemp_corr_unc",
              "units": "K",
              "name": "surface temperature correlated uncertainty"
            },
            {
              "id": "stemp_prop_unc",
              "units": "K",
              "name": "surface temperature propagated uncertainty"
            },
            {
              "id": "stemp_std",
              "units": "K",
              "name": "surface temperature standard deviation"
            },
            {
              "id": "stemp_unc",
              "units": "K",
              "name": "surface temperature uncertainty"
            },
            {
              "id": "stemp",
              "units": "K",
              "name": "surface temperature"
            }
          ]
        },
        {
          "id": "esacci.AEROSOL.satellite-orbit-frequency.L2P.AER_PRODUCTS.ATSR-2.ERS-2.ORAC.03-02.r1",
          "name": "ESA Aerosol Climate Change Initiative (Aerosol CCI): Level 2 aerosol products from ATSR2 (ORAC algorithm), Version 3.02",
          "fid": "b6751acb59b242bfa33af689c4778abd",
          "variables": [
            {
              "id": "aerosol_type",
              "units": "1",
              "name": "Best-guess aerosol type"
            },
            {
              "id": "cloud_fraction",
              "units": "1",
              "name": "Cloud fraction"
            },
            {
              "id": "fit_error",
              "units": "1",
              "name": "Cost function at solution"
            },
            {
              "id": "instrument_view",
              "units": "1",
              "name": "Instrument view"
            },
            {
              "id": "surface_type_number",
              "units": "1",
              "name": "Land / sea flag"
            },
            {
              "id": "quality_flag",
              "units": "1",
              "name": "Quality check results"
            },
            {
              "id": "relative_azimuth_at_center",
              "units": "degrees",
              "name": "Relative azimuth angle"
            },
            {
              "id": "iterations",
              "units": "1",
              "name": "Retrieval iterations"
            },
            {
              "id": "satellite_zenith_at_center",
              "units": "degrees",
              "name": "Satellite zenith angle"
            },
            {
              "id": "pixel_number",
              "units": "1",
              "name": "Sinusoidal pixel index"
            },
            {
              "id": "sun_zenith_at_center",
              "units": "degrees",
              "name": "Solar zenith angle"
            },
            {
              "id": "surface_reflectance1600",
              "units": "1",
              "name": "Surface bihemispherical reflectance at 1600 nm"
            },
            {
              "id": "surface_reflectance550",
              "units": "1",
              "name": "Surface bihemispherical reflectance at 550 nm"
            },
            {
              "id": "surface_reflectance670",
              "units": "1",
              "name": "Surface bihemispherical reflectance at 670 nm"
            },
            {
              "id": "surface_reflectance870",
              "units": "1",
              "name": "Surface bihemispherical reflectance at 870 nm"
            },
            {
              "id": "AOD550_uncertainty",
              "units": "1",
              "name": "Uncertainty on AOT at 550 nm"
            },
            {
              "id": "AOD870_uncertainty",
              "units": "1",
              "name": "Uncertainty on AOT at 870 nm"
            },
            {
              "id": "REFF_uncertainty",
              "units": "microns",
              "name": "Uncertainty on aerosol effective radius"
            },
            {
              "id": "surface_reflectance1600_uncertainty",
              "units": "1",
              "name": "Uncertainty on surface reflectance at 1600 nm"
            },
            {
              "id": "surface_reflectance550_uncertainty",
              "units": "1",
              "name": "Uncertainty on surface reflectance at 550 nm"
            },
            {
              "id": "surface_reflectance670_uncertainty",
              "units": "1",
              "name": "Uncertainty on surface reflectance at 670nm"
            },
            {
              "id": "surface_reflectance870_uncertainty",
              "units": "1",
              "name": "Uncertainty on surface reflectance at 870 nm"
            },
            {
              "id": "ANG550_870",
              "units": "1",
              "name": "aerosol Angstrom exponent between 550 and 870 nm"
            },
            {
              "id": "AAOD550",
              "units": "1",
              "name": "aerosol absorption optical thickness at 550 nm"
            },
            {
              "id": "REFF",
              "units": "microns",
              "name": "aerosol effective radius"
            },
            {
              "id": "AOD1600",
              "units": "1",
              "name": "aerosol optical thickness at 1600 nm"
            },
            {
              "id": "AOD550",
              "units": "1",
              "name": "aerosol optical thickness at 550 nm"
            },
            {
              "id": "AOD670",
              "units": "1",
              "name": "aerosol optical thickness at 670 nm"
            },
            {
              "id": "AOD870",
              "units": "1",
              "name": "aerosol optical thickness at 870 nm"
            },
            {
              "id": "D_AOD550",
              "units": "1",
              "name": "dust aerosol optical thickness at 550 nm"
            },
            {
              "id": "FM_AOD550",
              "units": "1",
              "name": "fine-mode aerosol optical thickness at 550 nm"
            }
          ]
        }
      ]
    }
  ]
}